qualisys.py
qualisys-0.2.0.dist-info/metadata.json
qualisys-0.2.0.dist-info/DESCRIPTION.rst
qualisys-0.2.0.dist-info/WHEEL
qualisys-0.2.0.dist-info/RECORD
qualisys-0.2.0.dist-info/METADATA
qualisys-0.2.0.dist-info/top_level.txt
