Metadata-Version: 2.0
Name: qualisys
Version: 0.2.0
Summary: Import data from Qualisys Track Manager into pandas.
Home-page: https://bitbucket.org/hharrison/python-qualisys
Author: Henry S. Harrison
Author-email: henry.schafer.harrison@gmail.com
License: MIT
Download-URL: https://bitbucket.org/hharrison/python-qualisys/get/default.tar.gz
Keywords: qualisys qtm motion-capture import biomechanics
Platform: UNKNOWN
Classifier: Programming Language :: Python
Classifier: Programming Language :: Python :: 3
Classifier: License :: OSI Approved :: MIT License
Classifier: Operating System :: OS Independent
Classifier: Development Status :: 3 - Alpha
Classifier: Intended Audience :: Science/Research
Classifier: Topic :: Utilities
Classifier: Topic :: Scientific/Engineering
Requires-Dist: numpy
Requires-Dist: pandas
